insultsmode/__init__.py
insultsmode/main.py
insultsmode-1.0.2.dist-info/LICENSE
insultsmode-1.0.2.dist-info/METADATA
insultsmode-1.0.2.dist-info/WHEEL
insultsmode-1.0.2.dist-info/top_level.txt
insultsmode-1.0.2.dist-info/RECORD
